{"id":"BAmaUw","label":"Taiwan Railways Station","transform":{"translateX":0,"translateY":0,"scale":1,"rotate":0},"version":2,"type":"Station","svgs":[{"id":"id_zZYDvhsztW","type":"g","label":"StationType","attrs":{"x":"1\"0\"","y":"1\"0\""},"children":[{"id":"id_HThocfERIk","type":"circle","label":"StationTypeBorder","attrs":{"x":"1\"0\"","y":"1\"0\"","r":"1\"10\"","opacity":"1\"1\"","fill":"1\"white\"","stroke":"2color[2]","strokeWidth":"1\"2\""}},{"id":"id_pQNpFpXtqZ","type":"text","label":"StationTypeText","attrs":{"x":"1\"0\"","y":"1\"0\"","_rmp_children_text":"3StationType[0]","opacity":"1\"1\"","fill":"1\"black\"","className":"1\"rmp-name__en\"","textAnchor":"1\"middle\"","fontSize":"1\"12\"","alignment-baseline":"1\"central\""}}]},{"id":"id_QXQHRWglOx","type":"rect","label":"StationIDBorder","attrs":{"x":"1\"-15\"","y":"1\"8\"","width":"1\"30\"","height":"1\"14\"","rx":"1\"2\"","ry":"1\"2\"","opacity":"1\"1\"","fill":"1\"white\"","stroke":"2color[2]","storkeWidth":"1\"2\""}},{"id":"id_wlRrfgwNqg","type":"text","label":"StationIDText","attrs":{"x":"1\"0\"","y":"1\"19\"","_rmp_children_text":"2StationID","opacity":"1\"1\"","fill":"1\"black\"","className":"1\"rmp-name__en\"","textAnchor":"1\"middle\"","fontSize":"1\"12\"","alignment-baseline":"1\"top\""}},{"id":"id_GkUtPohEmb","type":"g","label":"StationNameText","attrs":{"x":"3StationNameOffsetHorizontal===\"center\"?0 \t\t:StationNameOffsetHorizontal===\"left\"?-16 \t\t:StationNameOffsetHorizontal===\"right\"?16 \t\t:null","y":"3StationNameOffsetVertical===\"middle\"?0 \t\t:StationNameOffsetVertical===\"top\"?-22 \t\t:StationNameOffsetVertical===\"bottom\"?34 \t\t:null","transform":"3(StationNameDirection!=0?(\"translate(\" +  \t\t\t(StationNameOffsetHorizontal===\"center\"?\"+0\" \t\t\t:StationNameOffsetHorizontal===\"left\"?\"-12\" \t\t\t:StationNameOffsetHorizontal===\"right\"?\"+12\" \t\t\t:\"+0\") +  \t\t\t\" \" +  \t\t\t(StationNameOffsetVertical===\"middle\"?\"+0\" \t\t\t:StationNameOffsetVertical===\"top\"?\"-12\" \t\t\t:StationNameOffsetVertical===\"bottom\"?\"+18\" \t\t\t:\"+0\") +  \t\t\") \") \t\t:\"\") +  \t\t\"rotate(\" + (-1)*StationNameDirection + \")\" +  \t\t(StationNameDirection!=0?(\"translate(\" +  \t\t\t(StationNameOffsetHorizontal===\"center\"?\"-0\" \t\t\t:StationNameOffsetHorizontal===\"left\"?\"+12\" \t\t\t:StationNameOffsetHorizontal===\"right\"?\"-12\" \t\t\t:\"-0\") +  \t\t\t\" \" +  \t\t\t(StationNameOffsetVertical===\"middle\"?\"-0\" \t\t\t:StationNameOffsetVertical===\"top\"?\"+12\" \t\t\t:StationNameOffsetVertical===\"bottom\"?\"-12\" \t\t\t:\"-0\") +  \t\t\") \") \t\t:\"\")","transform-origin":"3\"0px 0px\""},"children":[{"id":"id_rWBrmUTows","type":"text","label":"StationNameEnglishText","attrs":{"x":"1\"0\"","y":"3-1+10","_rmp_children_text":"2StationNameEnglish","opacity":"1\"1\"","fill":"1\"black\"","className":"1\"rmp-name__en\"","textAnchor":"3StationNameOffsetHorizontal===\"center\"?\"middle\" \t:StationNameOffsetHorizontal===\"left\"?\"end\" \t:StationNameOffsetHorizontal===\"right\"?\"start\" \t:null","fontSize":"1\"10\""}},{"id":"id_AGgtsQpMcb","type":"text","label":"StationNameChineseText","attrs":{"x":"1\"0\"","y":"1\"0\"","_rmp_children_text":"2StationNameChinese","opacity":"1\"1\"","fill":"1\"black\"","className":"1\"rmp-name__en\"","textAnchor":"3StationNameOffsetHorizontal===\"center\"?\"middle\" \t:StationNameOffsetHorizontal===\"left\"?\"end\" \t:StationNameOffsetHorizontal===\"right\"?\"start\" \t:null","fontSize":"1\"12\""}}]}],"components":[{"id":"LHaoYqZuBG","label":"StationNameChinese","type":"textarea","defaultValue":"臺北","value":"臺北"},{"id":"xjjPgmGicK","label":"StationNameEnglish","type":"textarea","defaultValue":"Taipei"},{"id":"iTIfQVbEJd","label":"StationNameOffsetHorizontal","type":"text","defaultValue":"center","value":"center"},{"id":"YoLCIyDQjW","label":"StationNameOffsetVertical","type":"text","defaultValue":"bottom","value":"bottom"},{"id":"LQhalIjeJR","label":"StationNameDirection","type":"number","defaultValue":"0","value":"0"},{"id":"WyHPnTzMLW","label":"StationType","type":"text","defaultValue":"○特等站","value":"○特等站"},{"id":"ywZByOKbJl","label":"StationID","type":"text","defaultValue":"1000"}],"color":{"id":"color","label":"color","type":"color","defaultValue":["taipei","tr","#020281","#fff"]},"core":"id_HThocfERIk"}