<?xml version="1.0" encoding="UTF-8"?>
<!DOCTYPE mrt-stalist SYSTEM "./dtd/mrt_stalist.dtd">
<mrt-stalist>
	<group letter="A">
		
	</group>
	<group letter="B">
		
	</group>
	<group letter="C">
		
	</group>
	<group letter="D">
		
	</group>
	<group letter="E">
		
	</group>
	<group letter="F">
		
	</group>
	<group letter="G">
		
	</group>
	<group letter="H">
		
	</group>
	<group letter="I">
		
	</group>
	<group letter="J">
		
	</group>
	<group letter="K">
		
	</group>
	<group letter="L">
		
	</group>
	<group letter="M">
		<sta>
			<sta-name-zhtw>木柵</sta-name-zhtw>
			<sta-name-en>Muzha</sta-name-en>
			<route-and-stanos>
				<route-and-stano place="TP" route="BR" stano="02"/>
			</route-and-stanos>
		</sta>
	</group>
	<group letter="N">
		
	</group>
	<group letter="O">
		
	</group>
	<group letter="P">
		
	</group>
	<group letter="Q">
		
	</group>
	<group letter="R">
		
	</group>
	<group letter="S">
		
	</group>
	<group letter="T">
		<sta>
			<sta-name-zhtw>台北車站</sta-name-zhtw>
			<sta-name-en>Taipei Main Station</sta-name-en>
			<route-and-stanos>
				<route-and-stano place="TP" route="R" stano="10"/>
				<route-and-stano place="TP" route="BL" stano="12"/>
				<route-and-stano place="TY" route="A" stano="1"/>
			</route-and-stanos>
		</sta>
		<sta>
			<sta-name-zhtw>動物園</sta-name-zhtw>
			<sta-name-en>Taipei Zoo</sta-name-en>
			<route-and-stanos>
				<route-and-stano place="TP" route="BR" stano="01"/>
				<route-and-stano place="NT" route="Y" stano="01" no-service="true"/>
				<route-and-stano place="NT" route="S" stano="01" no-service="true"/>
			</route-and-stanos>
		</sta>
	</group>
	<group letter="U">
		
	</group>
	<group letter="V">
		
	</group>
	<group letter="W">
		
	</group>
	<group letter="X">
		
	</group>
	<group letter="Y">
		
	</group>
	<group letter="Z">
		
	</group>
</mrt-stalist>